slimeda/__init__.py
slimeda/cat_unique_counts.py
slimeda/corr_map.py
slimeda/histogram.py
slimeda/miss_counts.py
slimeda/slimeda.py
slimeda-0.1.6.dist-info/LICENSE
slimeda-0.1.6.dist-info/WHEEL
slimeda-0.1.6.dist-info/METADATA
slimeda-0.1.6.dist-info/RECORD
