Metadata-Version: 2.1
Name: slimeda
Version: 0.1.6
Summary: Slim version of EDA processing Python package
License: MIT
Author: Simon Guo
Requires-Python: >=3.9,<4.0
Classifier: License :: OSI Approved :: MIT License
Classifier: Programming Language :: Python :: 3
Classifier: Programming Language :: Python :: 3.10
Classifier: Programming Language :: Python :: 3.9
Requires-Dist: altair (>=4.2.0,<5.0.0)
Requires-Dist: numpy (>=1.22.1,<2.0.0)
Requires-Dist: pandas (>=1.3.5,<2.0.0)
